tests/__init__.py
tests/test_api.py
tests/test_auth.py
tests/test_crypto.py
tests/test_database.py
tests/test_integration.py
tests/test_performance.py
tests/test_ssh.py
valtdb/__init__.py
valtdb/api.py
valtdb/auth.py
valtdb/cli.py
valtdb/crypto.py
valtdb/database.py
valtdb/exceptions.py
valtdb/index.py
valtdb/keypair.py
valtdb/query.py
valtdb/schema.py
valtdb/ssh.py
valtdb/table.py
valtdb/crypto/__init__.py
valtdb/crypto/encryption.py
valtdb/crypto/hashing.py
valtdb-1.0.0.dist-info/LICENSE
valtdb-1.0.0.dist-info/METADATA
valtdb-1.0.0.dist-info/WHEEL
valtdb-1.0.0.dist-info/entry_points.txt
valtdb-1.0.0.dist-info/top_level.txt
valtdb-1.0.0.dist-info/RECORD
